Metadata-Version: 2.3
Name: pretzelai
Version: 4.2.11
Summary: Pretzel is a fork of JupyterLab that improves the user experience of the JupyterLab computational environment.
Project-URL: Homepage, https://withpretzel.com
Project-URL: Changelog, https://withpretzel.com/changelog
Project-URL: Documentation, https://withpretzel.com/docs
Project-URL: Source, https://github.com/pretzelai/pretzelai
Project-URL: Issues, https://github.com/pretzelai/pretzelai/issues/new/choose
Project-URL: Pypi, https://pypi.org/project/pretzelai
Author-email: Pretzel AI GmbH <founders@pretzel.ai>
License: Pretzel is a fork of Project Jupyter, which is licensed under the terms
License-File: LICENSE
License-File: LICENSE_AGPLv3
Keywords: ipython,jupyter
Classifier: Development Status :: 5 - Production/Stable
Classifier: Framework :: Jupyter
Classifier: Framework :: Jupyter :: JupyterLab
Classifier: Framework :: Jupyter :: JupyterLab :: 4
Classifier: Intended Audience :: Developers
Classifier: Intended Audience :: Science/Research
Classifier: Intended Audience :: System Administrators
Classifier: License :: OSI Approved :: BSD License
Classifier: Programming Language :: Python
Classifier: Programming Language :: Python :: 3.8
Classifier: Programming Language :: Python :: 3.9
Classifier: Programming Language :: Python :: 3.10
Classifier: Programming Language :: Python :: 3.11
Classifier: Programming Language :: Python :: 3.12
Requires-Python: >=3.8
Requires-Dist: async-lru>=1.0.0
Requires-Dist: httpx>=0.25.0
Requires-Dist: importlib-metadata>=4.8.3; python_version < '3.10'
Requires-Dist: importlib-resources>=1.4; python_version < '3.9'
Requires-Dist: ipykernel>=6.5.0
Requires-Dist: jinja2>=3.0.3
Requires-Dist: jupyter-core
Requires-Dist: jupyter-lsp>=2.0.0
Requires-Dist: jupyter-server<3,>=2.4.0
Requires-Dist: jupyterlab-server<3,>=2.27.1
Requires-Dist: notebook-shim>=0.2
Requires-Dist: packaging
Requires-Dist: pretzelai-server>=0.1.3
Requires-Dist: tomli>=1.2.2; python_version < '3.11'
Requires-Dist: tornado>=6.2.0
Requires-Dist: traitlets
Provides-Extra: dev
Requires-Dist: build; extra == 'dev'
Requires-Dist: bump2version; extra == 'dev'
Requires-Dist: coverage; extra == 'dev'
Requires-Dist: hatch; extra == 'dev'
Requires-Dist: pre-commit; extra == 'dev'
Requires-Dist: pytest-cov; extra == 'dev'
Requires-Dist: ruff==0.3.5; extra == 'dev'
Provides-Extra: docs
Requires-Dist: jsx-lexer; extra == 'docs'
Requires-Dist: myst-parser; extra == 'docs'
Requires-Dist: pydata-sphinx-theme>=0.13.0; extra == 'docs'
Requires-Dist: pytest; extra == 'docs'
Requires-Dist: pytest-check-links; extra == 'docs'
Requires-Dist: pytest-jupyter; extra == 'docs'
Requires-Dist: sphinx-copybutton; extra == 'docs'
Requires-Dist: sphinx<7.3.0,>=1.8; extra == 'docs'
Provides-Extra: docs-screenshots
Requires-Dist: altair==5.3.0; extra == 'docs-screenshots'
Requires-Dist: ipython==8.16.1; extra == 'docs-screenshots'
Requires-Dist: ipywidgets==8.1.2; extra == 'docs-screenshots'
Requires-Dist: jupyterlab-geojson==3.4.0; extra == 'docs-screenshots'
Requires-Dist: jupyterlab-language-pack-zh-cn==4.1.post2; extra == 'docs-screenshots'
Requires-Dist: matplotlib==3.8.3; extra == 'docs-screenshots'
Requires-Dist: nbconvert>=7.0.0; extra == 'docs-screenshots'
Requires-Dist: pandas==2.2.1; extra == 'docs-screenshots'
Requires-Dist: scipy==1.12.0; extra == 'docs-screenshots'
Requires-Dist: vega-datasets==0.9.0; extra == 'docs-screenshots'
Provides-Extra: test
Requires-Dist: coverage; extra == 'test'
Requires-Dist: pytest-check-links>=0.7; extra == 'test'
Requires-Dist: pytest-console-scripts; extra == 'test'
Requires-Dist: pytest-cov; extra == 'test'
Requires-Dist: pytest-jupyter>=0.5.3; extra == 'test'
Requires-Dist: pytest-timeout; extra == 'test'
Requires-Dist: pytest-tornasync; extra == 'test'
Requires-Dist: pytest>=7.0; extra == 'test'
Requires-Dist: requests; extra == 'test'
Requires-Dist: requests-cache; extra == 'test'
Requires-Dist: virtualenv; extra == 'test'
Provides-Extra: upgrade-extension
Requires-Dist: copier<10,>=8; extra == 'upgrade-extension'
Requires-Dist: jinja2-time<0.3; extra == 'upgrade-extension'
Requires-Dist: pydantic<2.0; extra == 'upgrade-extension'
Requires-Dist: pyyaml-include<2.0; extra == 'upgrade-extension'
Requires-Dist: tomli-w<2.0; extra == 'upgrade-extension'
